metta_profiler/__init__.py
metta_profiler/iter_utils.py
metta_profiler/profiler.py
metta_profiler/time_utils.py
metta_profiler/trace.py
metta_profiler-0.1.1.dist-info/LICENSE
metta_profiler-0.1.1.dist-info/WHEEL
metta_profiler-0.1.1.dist-info/METADATA
metta_profiler-0.1.1.dist-info/RECORD
